{"cameraMode":{"drawMode":0,"name":"Shaded","section":"Shading Mode"},"sceneLighting":false,"audioPlay":false,"sceneViewState":{"m_AlwaysRefresh":false,"showFog":true,"showSkybox":false,"showFlares":true,"showImageEffects":true,"showParticleSystems":true,"showVisualEffectGraphs":true,"m_FxEnabled":true},"in2DMode":false,"pivot":{"x":46.68410873413086,"y":2.6140658855438234,"z":-9.719268798828125},"rotation":{"x":-0.0116115752607584,"y":-0.887269914150238,"z":0.4605811536312103,"w":-0.02237214520573616},"size":0.264975368976593,"orthographic":false}